[
  {
    "title": "Peace Art_L6",
    "link_thumb": "https://live.staticflickr.com/65535/51788141785_1a40768f79_o.gif",
    "id_album": "437172984",
    "total": 29,
    "size_max_detail_page": 1,
    "list_detail": [
      {
        "index_page": 0,
        "link_page": "https://github.com/lmbstudiocontact/mb5_dt_alb_0/raw/main/14132021_dta_437172984_index_0.json"
      }
    ]
  },
  {
    "title": "Star War_L5",
    "link_thumb": "https://live.staticflickr.com/65535/51787872559_01d40c9e74_o.gif",
    "id_album": "-1637191762",
    "total": 2,
    "size_max_detail_page": 1,
    "list_detail": [
      {
        "index_page": 0,
        "link_page": "https://github.com/lmbstudiocontact/mb5_dt_alb_0/raw/main/14132021_dta_-1637191762_index_0.json"
      }
    ]
  },
  {
    "title": "Other_L7",
    "link_thumb": "https://live.staticflickr.com/65535/51787287706_7ed721623a_o.gif",
    "id_album": "-1106495206",
    "total": 57,
    "size_max_detail_page": 2,
    "list_detail": [
      {
        "index_page": 0,
        "link_page": "https://github.com/lmbstudiocontact/mb5_dt_alb_0/raw/main/14132021_dta_-1106495206_index_0.json"
      },
      {
        "index_page": 1,
        "link_page": "https://github.com/lmbstudiocontact/mb5_dt_alb_0/raw/main/14132021_dta_-1106495206_index_1.json"
      }
    ]
  },
  {
    "title": "Fox Art_L4",
    "link_thumb": "https://live.staticflickr.com/65535/51787482753_1d827173e2_o.gif",
    "id_album": "-646110859",
    "total": 7,
    "size_max_detail_page": 1,
    "list_detail": [
      {
        "index_page": 0,
        "link_page": "https://github.com/lmbstudiocontact/mb5_dt_alb_0/raw/main/14132021_dta_-646110859_index_0.json"
      }
    ]
  },
  {
    "title": "Kitty & My Melody_L3",
    "link_thumb": "https://live.staticflickr.com/65535/51787506038_e768283934_o.gif",
    "id_album": "-378480543",
    "total": 76,
    "size_max_detail_page": 2,
    "list_detail": [
      {
        "index_page": 0,
        "link_page": "https://github.com/lmbstudiocontact/mb5_dt_alb_0/raw/main/14132021_dta_-378480543_index_0.json"
      },
      {
        "index_page": 1,
        "link_page": "https://github.com/lmbstudiocontact/mb5_dt_alb_0/raw/main/14132021_dta_-378480543_index_1.json"
      }
    ]
  },
  {
    "title": "Dragon Art_L3",
    "link_thumb": "https://live.staticflickr.com/65535/51788091280_50856969e4_o.gif",
    "id_album": "2059014000",
    "total": 13,
    "size_max_detail_page": 1,
    "list_detail": [
      {
        "index_page": 0,
        "link_page": "https://github.com/lmbstudiocontact/mb5_dt_alb_0/raw/main/14132021_dta_2059014000_index_0.json"
      }
    ]
  },
  {
    "title": "Horror Art_L2",
    "link_thumb": "https://live.staticflickr.com/65535/51787257531_bf512b12f6_o.gif",
    "id_album": "529377272",
    "total": 41,
    "size_max_detail_page": 1,
    "list_detail": [
      {
        "index_page": 0,
        "link_page": "https://github.com/lmbstudiocontact/mb5_dt_alb_0/raw/main/14132021_dta_529377272_index_0.json"
      }
    ]
  },
  {
    "title": "Horror Art_L3",
    "link_thumb": "https://live.staticflickr.com/65535/51787495718_f7ff184cc5_o.gif",
    "id_album": "529377273",
    "total": 41,
    "size_max_detail_page": 1,
    "list_detail": [
      {
        "index_page": 0,
        "link_page": "https://github.com/lmbstudiocontact/mb5_dt_alb_0/raw/main/14132021_dta_529377273_index_0.json"
      }
    ]
  },
  {
    "title": "Butterfly_L4",
    "link_thumb": "https://live.staticflickr.com/65535/51786374502_c6a44983ea_o.gif",
    "id_album": "657564372",
    "total": 6,
    "size_max_detail_page": 1,
    "list_detail": [
      {
        "index_page": 0,
        "link_page": "https://github.com/lmbstudiocontact/mb5_dt_alb_0/raw/main/14132021_dta_657564372_index_0.json"
      }
    ]
  }
]